sudtools/__init__.py
sudtools/cmdline.so
sudtools/execute.so
sudtools/hub_file_utils.so
sudtools/user.so
sudtools/utils.so
sudtools-1.3.0.dist-info/METADATA
sudtools-1.3.0.dist-info/WHEEL
sudtools-1.3.0.dist-info/entry_points.txt
sudtools-1.3.0.dist-info/top_level.txt
sudtools-1.3.0.dist-info/RECORD
